{
  "title": "Kunst & Literatur (C1)",
  "language": "de",
  "words": [
    {
      "term": "die Ästhetik",
      "type": "Noun",
      "example": "Die *** des Films hat mich tief beeindruckt.",
      "meaning_tr": "estetik",
      "meaning_en": "aesthetics",
      "meaning_uk": "естетика",
      "meaning_es": "estética"
    },
    {
      "term": "die Epoche",
      "type": "Noun",
      "example": "Diese literarische *** wird oft unterschätzt.",
      "meaning_tr": "çağ, dönem",
      "meaning_en": "epoch",
      "meaning_uk": "епоха",
      "meaning_es": "época"
    },
    {
      "term": "die Allegorie",
      "type": "Noun",
      "example": "Das Gedicht ist eine *** auf den menschlichen Hochmut.",
      "meaning_tr": "alegori",
      "meaning_en": "allegory",
      "meaning_uk": "алегорія",
      "meaning_es": "alegoría"
    },
    {
      "term": "die Ambivalenz",
      "type": "Noun",
      "example": "Die *** des Charakters macht ihn so interessant.",
      "meaning_tr": "ikirciklilik",
      "meaning_en": "ambivalence",
      "meaning_uk": "амбівалентність",
      "meaning_es": "ambivalencia"
    },
    {
      "term": "die Avantgarde",
      "type": "Noun",
      "example": "Die *** forderte radikale Veränderungen in der Malerei.",
      "meaning_tr": "öncü sanat",
      "meaning_en": "avant-garde",
      "meaning_uk": "авангард",
      "meaning_es": "vanguardia"
    },
    {
      "term": "die Interpretation",
      "type": "Noun",
      "example": "Es gibt viele Wege zur *** dieses Textes.",
      "meaning_tr": "yorum",
      "meaning_en": "interpretation",
      "meaning_uk": "інтерпретація",
      "meaning_es": "interpretación"
    },
    {
      "term": "die Metapher",
      "type": "Noun",
      "example": "Er benutzte eine kraftvolle ***, um den Schmerz zu beschreiben.",
      "meaning_tr": "metafor",
      "meaning_en": "metaphor",
      "meaning_uk": "метафора",
      "meaning_es": "metáfora"
    },
    {
      "term": "die Novelle",
      "type": "Noun",
      "example": "Ich habe eine spannende *** von Thomas Mann gelesen.",
      "meaning_tr": "uzun öykü, kısa roman",
      "meaning_en": "novella",
      "meaning_uk": "новела",
      "meaning_es": "novela corta"
    },
    {
      "term": "die Rezension",
      "type": "Noun",
      "example": "Die *** in der Zeitung war sehr kritisch.",
      "meaning_tr": "eleştiri, inceleme",
      "meaning_en": "review",
      "meaning_uk": "рецензія",
      "meaning_es": "reseña"
    },
    {
      "term": "die Synästhesie",
      "type": "Noun",
      "example": "In der Lyrik wird oft die *** verwendet.",
      "meaning_tr": "duyu aktarımı",
      "meaning_en": "synesthesia",
      "meaning_uk": "синестезія",
      "meaning_es": "sinestesia"
    },
    {
      "term": "die Zäsur",
      "type": "Noun",
      "example": "Dieses Ereignis markierte eine *** in seinem künstlerischen Schaffen.",
      "meaning_tr": "kesinti, dönüm noktası",
      "meaning_en": "caesura, turning point",
      "meaning_uk": "цезура, переломний момент",
      "meaning_es": "cesura, punto de inflexión"
    },
    {
      "term": "die Gattung",
      "type": "Noun",
      "example": "Welche literarische *** bevorzugst du?",
      "meaning_tr": "tür",
      "meaning_en": "genre",
      "meaning_uk": "жанр",
      "meaning_es": "género"
    },
    {
      "term": "die Prosa",
      "type": "Noun",
      "example": "Er schreibt sowohl Lyrik als auch ***.",
      "meaning_tr": "düzyazı",
      "meaning_en": "prose",
      "meaning_uk": "проза",
      "meaning_es": "prosa"
    },
    {
      "term": "die Lyrik",
      "type": "Noun",
      "example": "Die moderne *** ist oft schwer zu verstehen.",
      "meaning_tr": "şiir",
      "meaning_en": "poetry",
      "meaning_uk": "лірика",
      "meaning_es": "poesía"
    },
    {
      "term": "die Dramatik",
      "type": "Noun",
      "example": "Die *** ist neben Epik und Lyrik eine Grundform der Literatur.",
      "meaning_tr": "tiyatro sanatı",
      "meaning_en": "drama",
      "meaning_uk": "драматургія",
      "meaning_es": "dramática"
    },
    {
      "term": "die Intention",
      "type": "Noun",
      "example": "Was war die künstlerische *** hinter diesem Werk?",
      "meaning_tr": "niyet",
      "meaning_en": "intention",
      "meaning_uk": "намір",
      "meaning_es": "intención"
    },
    {
      "term": "die Komposition",
      "type": "Noun",
      "example": "Die *** des Bildes ist sehr ausgewogen.",
      "meaning_tr": "kompozisyon",
      "meaning_en": "composition",
      "meaning_uk": "композиція",
      "meaning_es": "composición"
    },
    {
      "term": "die Ästhetisierung",
      "type": "Noun",
      "example": "Er kritisierte die *** von Gewalt in diesem Film.",
      "meaning_tr": "estetikleştirme",
      "meaning_en": "aestheticization",
      "meaning_uk": "естетизація",
      "meaning_es": "estetización"
    },
    {
      "term": "die Abstraktion",
      "type": "Noun",
      "example": "Die *** in seiner Malerei nimmt immer weiter zu.",
      "meaning_tr": "soyutlama",
      "meaning_en": "abstraction",
      "meaning_uk": "абстракція",
      "meaning_es": "abstracción"
    },
    {
      "term": "die Fiktion",
      "type": "Noun",
      "example": "Die Grenze zwischen Realität und *** verschwimmt hier.",
      "meaning_tr": "kurgu",
      "meaning_en": "fiction",
      "meaning_uk": "фікція",
      "meaning_es": "ficción"
    },
    {
      "term": "der Duktus",
      "type": "Noun",
      "example": "Man erkennt den persönlichen *** des Malers sofort.",
      "meaning_tr": "üslup, fırça vuruşu",
      "meaning_en": "style, brushstroke",
      "meaning_uk": "стиль, манера письма",
      "meaning_es": "estilo, trazo"
    },
    {
      "term": "der Kanon",
      "type": "Noun",
      "example": "Dieses Buch gehört zum literarischen ***.",
      "meaning_tr": "kanon, temel eserler bütünü",
      "meaning_en": "canon",
      "meaning_uk": "канон",
      "meaning_es": "canon"
    },
    {
      "term": "der Kontrast",
      "type": "Noun",
      "example": "Der *** zwischen Licht und Schatten ist faszinierend.",
      "meaning_tr": "zıtlık",
      "meaning_en": "contrast",
      "meaning_uk": "контраст",
      "meaning_es": "contraste"
    },
    {
      "term": "der Zeitgeist",
      "type": "Noun",
      "example": "Das Werk spiegelt den *** der 20er Jahre wider.",
      "meaning_tr": "zamanın ruhu",
      "meaning_en": "spirit of the age",
      "meaning_uk": "дух часу",
      "meaning_es": "espíritu de la época"
    },
    {
      "term": "der Narrativ",
      "type": "Noun",
      "example": "Das dominante *** muss hinterfragt werden.",
      "meaning_tr": "anlatı",
      "meaning_en": "narrative",
      "meaning_uk": "наратив",
      "meaning_es": "narrativa"
    },
    {
      "term": "der Eklektizismus",
      "type": "Noun",
      "example": "Sein Stil zeichnet sich durch *** aus.",
      "meaning_tr": "eklektisizm",
      "meaning_en": "eclecticism",
      "meaning_uk": "еклектизм",
      "meaning_es": "eclecticismo"
    },
    {
      "term": "der Expressionismus",
      "type": "Noun",
      "example": "Der *** war eine bedeutende Kunstbewegung.",
      "meaning_tr": "dışavurumculuk",
      "meaning_en": "expressionism",
      "meaning_uk": "експресіонізм",
      "meaning_es": "expresionismo"
    },
    {
      "term": "der Realismus",
      "type": "Noun",
      "example": "Er wandte sich vom *** ab und zur Abstraktion hin.",
      "meaning_tr": "gerçekçilik",
      "meaning_en": "realism",
      "meaning_uk": "реалізм",
      "meaning_es": "realismo"
    },
    {
      "term": "der Subtext",
      "type": "Noun",
      "example": "Man muss auf den *** des Gesprächs achten.",
      "meaning_tr": "alt metin",
      "meaning_en": "subtext",
      "meaning_uk": "підтекст",
      "meaning_es": "subtexto"
    },
    {
      "term": "der Protagonist",
      "type": "Noun",
      "example": "Der *** durchläuft eine enorme Entwicklung.",
      "meaning_tr": "başkahraman",
      "meaning_en": "protagonist",
      "meaning_uk": "протагоніст",
      "meaning_es": "protagonista"
    },
    {
      "term": "das Exponat",
      "type": "Noun",
      "example": "Dieses *** ist das Herzstück der Ausstellung.",
      "meaning_tr": "sergi parçası",
      "meaning_en": "exhibit",
      "meaning_uk": "експонат",
      "meaning_es": "exhibición"
    },
    {
      "term": "das Sujet",
      "type": "Noun",
      "example": "Das *** des Gemäldes ist eine mythologische Szene.",
      "meaning_tr": "konu, tema",
      "meaning_en": "subject matter",
      "meaning_uk": "сюжет, тема",
      "meaning_es": "sujeto, tema"
    },
    {
      "term": "das Fragment",
      "type": "Noun",
      "example": "Der Roman blieb ein ***.",
      "meaning_tr": "parça, fragman",
      "meaning_en": "fragment",
      "meaning_uk": "фрагмент",
      "meaning_es": "fragmento"
    },
    {
      "term": "das Repertoire",
      "type": "Noun",
      "example": "Das *** des Orchesters ist sehr vielfältig.",
      "meaning_tr": "repertuvar",
      "meaning_en": "repertoire",
      "meaning_uk": "репертуар",
      "meaning_es": "repertorio"
    },
    {
      "term": "das Paradoxon",
      "type": "Noun",
      "example": "Die Geschichte basiert auf einem ***.",
      "meaning_tr": "paradoks",
      "meaning_en": "paradox",
      "meaning_uk": "парадокс",
      "meaning_es": "paradoja"
    },
    {
      "term": "das Kolorit",
      "type": "Noun",
      "example": "Das warme *** des Bildes erzeugt eine ruhige Stimmung.",
      "meaning_tr": "renk tonu, atmosfer",
      "meaning_en": "coloring, tone",
      "meaning_uk": "колорит",
      "meaning_es": "colorido"
    },
    {
      "term": "das Plagiat",
      "type": "Noun",
      "example": "Der Autor wurde des ***s beschuldigt.",
      "meaning_tr": "intihal",
      "meaning_en": "plagiarism",
      "meaning_uk": "плагіат",
      "meaning_es": "plagio"
    },
    {
      "term": "analysieren",
      "type": "Verb",
      "example": "Wir müssen das Gedicht genau ***.",
      "meaning_tr": "analiz etmek",
      "meaning_en": "to analyze",
      "meaning_uk": "аналізувати",
      "meaning_es": "analizar"
    },
    {
      "term": "interpretieren",
      "type": "Verb",
      "example": "Wie würdest du diese Szene ***?",
      "meaning_tr": "yorumlamak",
      "meaning_en": "to interpret",
      "meaning_uk": "інтерпретувати",
      "meaning_es": "interpretar"
    },
    {
      "term": "inszenieren",
      "type": "Verb",
      "example": "Der Regisseur hat das Stück modern ***.",
      "meaning_tr": "sahnelemek",
      "meaning_en": "to stage, to direct",
      "meaning_uk": "інсценувати",
      "meaning_es": "poner en escena"
    },
    {
      "term": "stilisieren",
      "type": "Verb",
      "example": "Er versucht, seine Figur zum Helden zu ***.",
      "meaning_tr": "biçemleştirmek",
      "meaning_en": "to stylize",
      "meaning_uk": "стилізувати",
      "meaning_es": "estilizar"
    },
    {
      "term": "reflektieren",
      "type": "Verb",
      "example": "Das Werk soll die gesellschaftlichen Zustände ***.",
      "meaning_tr": "yansıtmak",
      "meaning_en": "to reflect",
      "meaning_uk": "рефлексувати",
      "meaning_es": "reflejar"
    },
    {
      "term": "darstellen",
      "type": "Verb",
      "example": "Der Maler will hier einen Moment der Stille ***.",
      "meaning_tr": "tasvir etmek",
      "meaning_en": "to depict, to represent",
      "meaning_uk": "зображати",
      "meaning_es": "representar"
    },
    {
      "term": "rezipieren",
      "type": "Verb",
      "example": "Wie wird dieses Werk vom Publikum ***?",
      "meaning_tr": "alımlamak, tüketmek",
      "meaning_en": "to receive, to perceive",
      "meaning_uk": "сприймати",
      "meaning_es": "recibir, percibir"
    },
    {
      "term": "abstrakt",
      "type": "Adjective",
      "example": "Seine Kunst ist sehr ***.",
      "meaning_tr": "soyut",
      "meaning_en": "abstract",
      "meaning_uk": "абстрактний",
      "meaning_es": "abstracto"
    },
    {
      "term": "subtil",
      "type": "Adjective",
      "example": "Der Autor setzt *** Ironie ein.",
      "meaning_tr": "ince, ustalıklı",
      "meaning_en": "subtle",
      "meaning_uk": "тонкий, ледь помітний",
      "meaning_es": "sutil"
    },
    {
      "term": "ambivalent",
      "type": "Adjective",
      "example": "Die Haltung des Künstlers bleibt ***.",
      "meaning_tr": "ikircikli",
      "meaning_en": "ambivalent",
      "meaning_uk": "амбівалентний",
      "meaning_es": "ambivalente"
    },
    {
      "term": "expressiv",
      "type": "Adjective",
      "example": "Er malt in einem sehr *** Stil.",
      "meaning_tr": "dışavurumcu",
      "meaning_en": "expressive",
      "meaning_uk": "експресивний",
      "meaning_es": "expresivo"
    },
    {
      "term": "fragmentarisch",
      "type": "Adjective",
      "example": "Die Handlung ist eher *** erzählt.",
      "meaning_tr": "parçalı",
      "meaning_en": "fragmentary",
      "meaning_uk": "фрагментарний",
      "meaning_es": "fragmentario"
    },
    {
      "term": "konventionell",
      "type": "Adjective",
      "example": "Er bricht mit *** Formen.",
      "meaning_tr": "geleneksel",
      "meaning_en": "conventional",
      "meaning_uk": "конвенційний",
      "meaning_es": "convencional"
    },
    {
      "term": "avantgardistisch",
      "type": "Adjective",
      "example": "Das Design wirkt sehr ***.",
      "meaning_tr": "öncü",
      "meaning_en": "avant-garde",
      "meaning_uk": "авангардний",
      "meaning_es": "vanguardista"
    },
    {
      "term": "allegorisch",
      "type": "Adjective",
      "example": "Die Figur ist *** zu verstehen.",
      "meaning_tr": "alegorik",
      "meaning_en": "allegorical",
      "meaning_uk": "алегоричний",
      "meaning_es": "alegórico"
    },
    {
      "term": "fiktiv",
      "type": "Adjective",
      "example": "Die Charaktere sind rein ***.",
      "meaning_tr": "kurgusal",
      "meaning_en": "fictional",
      "meaning_uk": "фіктивний",
      "meaning_es": "ficticio"
    },
    {
      "term": "ästhetisch",
      "type": "Adjective",
      "example": "Das ist ein sehr *** ansprechendes Design.",
      "meaning_tr": "estetik",
      "meaning_en": "aesthetic",
      "meaning_uk": "естетичний",
      "meaning_es": "estético"
    },
    {
      "term": "hinsichtlich",
      "type": "Preposition",
      "example": "*** der Komposition ist das Bild perfekt.",
      "meaning_tr": "bakımından",
      "meaning_en": "regarding",
      "meaning_uk": "стосовно",
      "meaning_es": "con respecto a"
    },
    {
      "term": "anlässlich",
      "type": "Preposition",
      "example": "*** der Ausstellung gibt es einen Katalog.",
      "meaning_tr": "vesilesiyle",
      "meaning_en": "on the occasion of",
      "meaning_uk": "з нагоди",
      "meaning_es": "con motivo de"
    },
    {
      "term": "mithin",
      "type": "Adverb",
      "example": "Das Werk ist *** als wegweisend zu bezeichnen.",
      "meaning_tr": "dolayısıyla, böylece",
      "meaning_en": "consequently",
      "meaning_uk": "отже",
      "meaning_es": "por consiguiente"
    },
    {
      "term": "nichtsdestotrotz",
      "type": "Conjunction",
      "example": "Der Film war lang, *** war er spannend.",
      "meaning_tr": "yine de",
      "meaning_en": "nevertheless",
      "meaning_uk": "тим не менш",
      "meaning_es": "no obstante"
    },
    {
      "term": "folglich",
      "type": "Adverb",
      "example": "Der Autor nutzte eine neue Technik, *** änderte sich der Stil.",
      "meaning_tr": "sonuç olarak",
      "meaning_en": "consequently",
      "meaning_uk": "отже",
      "meaning_es": "en consecuencia"
    },
    {
      "term": "indes",
      "type": "Adverb",
      "example": "Die Kritik war hart, *** blieb der Erfolg aus.",
      "meaning_tr": "bununla birlikte",
      "meaning_en": "however",
      "meaning_uk": "однак",
      "meaning_es": "sin embargo"
    }
  ]
}