{
  "title": "Educacion y Universidad (B1)",
  "language": "es",
  "words": [
    {
      "term": "la asignatura",
      "type": "Noun",
      "meaning_tr": "ders",
      "meaning_en": "subject",
      "meaning_uk": "предмет",
      "meaning_es": "materia de estudio",
      "example": "*** favorita de Juan es la historia."
    },
    {
      "term": "aprobar",
      "type": "Verb",
      "meaning_tr": "geçmek (sınav)",
      "meaning_en": "to pass",
      "meaning_uk": "скласти іспит",
      "meaning_es": "superar un examen",
      "example": "Espero *** el examen de matemáticas mañana."
    },
    {
      "term": "la beca",
      "type": "Noun",
      "meaning_tr": "burs",
      "meaning_en": "scholarship",
      "meaning_uk": "стипендія",
      "meaning_es": "ayuda económica para estudiar",
      "example": "Solicité *** para estudiar en el extranjero."
    },
    {
      "term": "el campus",
      "type": "Noun",
      "meaning_tr": "kampüs",
      "meaning_en": "campus",
      "meaning_uk": "кампус",
      "meaning_es": "recinto universitario",
      "example": "El *** de esta universidad es enorme."
    },
    {
      "term": "la carrera",
      "type": "Noun",
      "meaning_tr": "üniversite bölümü",
      "meaning_en": "degree / major",
      "meaning_uk": "факультет / спеціальність",
      "meaning_es": "estudios universitarios",
      "example": "Todavía no sé qué *** quiero estudiar."
    },
    {
      "term": "el catedrático",
      "type": "Noun",
      "meaning_tr": "profesör",
      "meaning_en": "professor",
      "meaning_uk": "професор",
      "meaning_es": "profesor titular de universidad",
      "example": "El *** dará una conferencia muy interesante."
    },
    {
      "term": "el coloquio",
      "type": "Noun",
      "meaning_tr": "panel / tartışma",
      "meaning_en": "colloquium / discussion",
      "meaning_uk": "дискусія",
      "meaning_es": "debate académico",
      "example": "Participaremos en un *** sobre literatura moderna."
    },
    {
      "term": "convalidar",
      "type": "Verb",
      "meaning_tr": "denklik almak",
      "meaning_en": "to validate / recognize",
      "meaning_uk": "підтвердити (диплом)",
      "meaning_es": "reconocer estudios previos",
      "example": "Tuve que *** mis notas de la universidad anterior."
    },
    {
      "term": "el curso",
      "type": "Noun",
      "meaning_tr": "kurs / eğitim yılı",
      "meaning_en": "course / academic year",
      "meaning_uk": "курс",
      "meaning_es": "periodo de enseñanza",
      "example": "Este *** académico empieza en septiembre."
    },
    {
      "term": "la docencia",
      "type": "Noun",
      "meaning_tr": "öğretim",
      "meaning_en": "teaching",
      "meaning_uk": "викладання",
      "meaning_es": "actividad de enseñar",
      "example": "Ella se dedica a la *** en la universidad."
    },
    {
      "term": "el doctorado",
      "type": "Noun",
      "meaning_tr": "doktora",
      "meaning_en": "PhD",
      "meaning_uk": "аспірантура / докторат",
      "meaning_es": "máximo grado académico",
      "example": "Está terminando su *** en biología."
    },
    {
      "term": "el examen",
      "type": "Noun",
      "meaning_tr": "sınav",
      "meaning_en": "exam",
      "meaning_uk": "іспит",
      "meaning_es": "prueba de conocimientos",
      "example": "Tengo un *** muy difícil la próxima semana."
    },
    {
      "term": "la facultad",
      "type": "Noun",
      "meaning_tr": "fakülte",
      "meaning_en": "faculty",
      "meaning_uk": "факультет",
      "meaning_es": "sección de una universidad",
      "example": "La *** de Medicina está cerrada por reformas."
    },
    {
      "term": "la formación",
      "type": "Noun",
      "meaning_tr": "eğitim",
      "meaning_en": "training / education",
      "meaning_uk": "освіта / підготовка",
      "meaning_es": "enseñanza recibida",
      "example": "Necesito más *** para este trabajo."
    },
    {
      "term": "el grado",
      "type": "Noun",
      "meaning_tr": "lisans derecesi",
      "meaning_en": "undergraduate degree",
      "meaning_uk": "ступінь бакалавра",
      "meaning_es": "título universitario",
      "example": "He terminado mi *** en ingeniería."
    },
    {
      "term": "el horario",
      "type": "Noun",
      "meaning_tr": "ders programı",
      "meaning_en": "schedule",
      "meaning_uk": "розклад",
      "meaning_es": "tiempo de clases",
      "example": "Consulta el *** en la página web."
    },
    {
      "term": "interdisciplinar",
      "type": "Adjective",
      "meaning_tr": "disiplinlerarası",
      "meaning_en": "interdisciplinary",
      "meaning_uk": "міждисциплінарний",
      "meaning_es": "que abarca varias disciplinas",
      "example": "Es un proyecto *** muy innovador."
    },
    {
      "term": "la investigación",
      "type": "Noun",
      "meaning_tr": "araştırma",
      "meaning_en": "research",
      "meaning_uk": "дослідження",
      "meaning_es": "estudio profundo",
      "example": "La *** científica es fundamental en la universidad."
    },
    {
      "term": "el laboratorio",
      "type": "Noun",
      "meaning_tr": "laboratuvar",
      "meaning_en": "laboratory",
      "meaning_uk": "лабораторія",
      "meaning_es": "lugar para experimentos",
      "example": "Los estudiantes están en el *** practicando."
    },
    {
      "term": "la lectura",
      "type": "Noun",
      "meaning_tr": "okuma parçası",
      "meaning_en": "reading",
      "meaning_uk": "читання",
      "meaning_es": "texto para estudiar",
      "example": "Hay una *** obligatoria para mañana."
    },
    {
      "term": "la matrícula",
      "type": "Noun",
      "meaning_tr": "kayıt (harcı)",
      "meaning_en": "enrollment / tuition fee",
      "meaning_uk": "реєстрація / навчання",
      "meaning_es": "inscripción en un curso",
      "example": "He pagado la *** de este semestre."
    },
    {
      "term": "la nota",
      "type": "Noun",
      "meaning_tr": "not",
      "meaning_en": "grade",
      "meaning_uk": "оцінка",
      "meaning_es": "calificación",
      "example": "Saqué una *** excelente en el examen final."
    },
    {
      "term": "objetivo",
      "type": "Adjective",
      "meaning_tr": "nesnel / tarafsız",
      "meaning_en": "objective",
      "meaning_uk": "об'єктивний",
      "meaning_es": "imparcial",
      "example": "Debemos ser *** al analizar los datos."
    },
    {
      "term": "el posgrado",
      "type": "Noun",
      "meaning_tr": "yüksek lisans",
      "meaning_en": "postgraduate degree",
      "meaning_uk": "післядипломна освіта",
      "meaning_es": "estudios tras el grado",
      "example": "Quiero hacer un *** en negocios."
    },
    {
      "term": "el profesorado",
      "type": "Noun",
      "meaning_tr": "öğretim kadrosu",
      "meaning_en": "teaching staff",
      "meaning_uk": "викладацький склад",
      "meaning_es": "conjunto de profesores",
      "example": "El *** de esta facultad es muy prestigioso."
    },
    {
      "term": "reprobar",
      "type": "Verb",
      "meaning_tr": "sınavdan kalmak",
      "meaning_en": "to fail",
      "meaning_uk": "провалити іспит",
      "meaning_es": "suspender un examen",
      "example": "No quiero *** esta asignatura otra vez."
    },
    {
      "term": "el seminario",
      "type": "Noun",
      "meaning_tr": "seminer",
      "meaning_en": "seminar",
      "meaning_uk": "семінар",
      "meaning_es": "clase especializada",
      "example": "Asistiré a un *** sobre historia antigua."
    },
    {
      "term": "el semestre",
      "type": "Noun",
      "meaning_tr": "yarıyıl",
      "meaning_en": "semester",
      "meaning_uk": "семестр",
      "meaning_es": "periodo de seis meses",
      "example": "Este *** tengo muchas clases prácticas."
    },
    {
      "term": "suspender",
      "type": "Verb",
      "meaning_tr": "sınavdan kalmak",
      "meaning_en": "to fail",
      "meaning_uk": "завалити іспит",
      "meaning_es": "no aprobar un examen",
      "example": "Si no estudias, vas a ***."
    },
    {
      "term": "la tesis",
      "type": "Noun",
      "meaning_tr": "tez",
      "meaning_en": "thesis",
      "meaning_uk": "дисертація",
      "meaning_es": "trabajo de investigación final",
      "example": "Estoy escribiendo mi *** doctoral."
    },
    {
      "term": "el título",
      "type": "Noun",
      "meaning_tr": "diploma",
      "meaning_en": "degree / diploma",
      "meaning_uk": "диплом",
      "meaning_es": "certificado de estudios",
      "example": "Recibiré mi *** en la ceremonia de graduación."
    },
    {
      "term": "universitario",
      "type": "Adjective",
      "meaning_tr": "üniversite ile ilgili",
      "meaning_en": "university (adj)",
      "meaning_uk": "університетський",
      "meaning_es": "relativo a la universidad",
      "example": "La vida *** es muy interesante."
    },
    {
      "term": "el aula",
      "type": "Noun",
      "meaning_tr": "sınıf / derslik",
      "meaning_en": "classroom",
      "meaning_uk": "аудиторія",
      "meaning_es": "sala de clase",
      "example": "Busca el *** número 12 para la clase."
    },
    {
      "term": "el decano",
      "type": "Noun",
      "meaning_tr": "dekan",
      "meaning_en": "dean",
      "meaning_uk": "декан",
      "meaning_es": "director de una facultad",
      "example": "El *** hablará con los estudiantes hoy."
    },
    {
      "term": "el expediente",
      "type": "Noun",
      "meaning_tr": "öğrenci dosyası / not dökümü",
      "meaning_en": "academic record",
      "meaning_uk": "академічна довідка",
      "meaning_es": "historial académico",
      "example": "Tengo un *** brillante en la universidad."
    }
  ]
}