{
  "title": "Critica de los Medios (B2)",
  "language": "es",
  "words": [
    {
      "term": "la veracidad",
      "type": "Noun",
      "meaning_tr": "doğruluk",
      "meaning_en": "truthfulness",
      "meaning_uk": "правдивість",
      "meaning_es": "cualidad de ser verdadero",
      "example": "Es fundamental cuestionar *** de las noticias que leemos."
    },
    {
      "term": "manipular",
      "type": "Verb",
      "meaning_tr": "manipüle etmek",
      "meaning_en": "to manipulate",
      "meaning_uk": "маніпулювати",
      "meaning_es": "intervenir con medios hábiles para alterar la realidad",
      "example": "Algunos medios intentan *** la opinión pública con titulares engañosos."
    },
    {
      "term": "sesgado",
      "type": "Adjective",
      "meaning_tr": "yanlı",
      "meaning_en": "biased",
      "meaning_uk": "упереджений",
      "meaning_es": "que carece de neutralidad",
      "example": "El artículo presenta un punto de vista claramente *** sobre el tema."
    },
    {
      "term": "el sensacionalismo",
      "type": "Noun",
      "meaning_tr": "sansasyonellik",
      "meaning_en": "sensationalism",
      "meaning_uk": "сенсаційність",
      "meaning_es": "exageración de los hechos para causar impacto",
      "example": "El *** vende periódicos, pero sacrifica la calidad informativa."
    },
    {
      "term": "verificar",
      "type": "Verb",
      "meaning_tr": "doğrulamak",
      "meaning_en": "to verify",
      "meaning_uk": "перевіряти",
      "meaning_es": "comprobar la veracidad de algo",
      "example": "Debemos *** las fuentes antes de compartir información en redes."
    },
    {
      "term": "la parcialidad",
      "type": "Noun",
      "meaning_tr": "taraflılık",
      "meaning_en": "partiality",
      "meaning_uk": "упередженість",
      "meaning_es": "falta de objetividad",
      "example": "La *** del periodista fue evidente durante la entrevista."
    },
    {
      "term": "fidedigno",
      "type": "Adjective",
      "meaning_tr": "güvenilir",
      "meaning_en": "reliable",
      "meaning_uk": "достовірний",
      "meaning_es": "que es digno de fe",
      "example": "Busca siempre una fuente *** para informarte sobre política."
    },
    {
      "term": "la desinformación",
      "type": "Noun",
      "meaning_tr": "yanlış bilgilendirme",
      "meaning_en": "disinformation",
      "meaning_uk": "дезінформація",
      "meaning_es": "información falsa dada deliberadamente",
      "example": "La lucha contra *** es un desafío clave en la era digital."
    },
    {
      "term": "difundir",
      "type": "Verb",
      "meaning_tr": "yaymak",
      "meaning_en": "to spread",
      "meaning_uk": "поширювати",
      "meaning_es": "propagar noticias o conocimientos",
      "example": "Es irresponsable *** rumores sin haber contrastado los datos."
    },
    {
      "term": "la objetividad",
      "type": "Noun",
      "meaning_tr": "nesnellik",
      "meaning_en": "objectivity",
      "meaning_uk": "об'єктивність",
      "meaning_es": "imparcialidad en el trato de la información",
      "example": "Mantener *** resulta difícil cuando el autor tiene intereses propios."
    },
    {
      "term": "el bulo",
      "type": "Noun",
      "meaning_tr": "yalan haber",
      "meaning_en": "hoax",
      "meaning_uk": "фейк",
      "meaning_es": "noticia falsa propalada con un fin",
      "example": "Aquel *** circuló por WhatsApp durante toda la semana."
    },
    {
      "term": "contrastar",
      "type": "Verb",
      "meaning_tr": "karşılaştırmak",
      "meaning_en": "to contrast/compare",
      "meaning_uk": "зіставляти",
      "meaning_es": "comparar datos para verificar su exactitud",
      "example": "Es necesario *** las versiones de ambos bandos antes de opinar."
    },
    {
      "term": "la línea editorial",
      "type": "Noun",
      "meaning_tr": "yayın politikası",
      "meaning_en": "editorial line",
      "meaning_uk": "редакційна політика",
      "meaning_es": "postura ideológica de un medio",
      "example": "La *** de este diario es claramente conservadora."
    },
    {
      "term": "tendencioso",
      "type": "Adjective",
      "meaning_tr": "eğilimli",
      "meaning_en": "tendentious",
      "meaning_uk": "тенденційний",
      "meaning_es": "que tiende a un fin determinado",
      "example": "El informe tiene un enfoque *** que busca influir en el lector."
    },
    {
      "term": "la censura",
      "type": "Noun",
      "meaning_tr": "sansür",
      "meaning_en": "censorship",
      "meaning_uk": "цензура",
      "meaning_es": "intervención que impide la libre expresión",
      "example": "La *** gubernamental limita la libertad de prensa en ese país."
    },
    {
      "term": "tergiversar",
      "type": "Verb",
      "meaning_tr": "saptırmak",
      "meaning_en": "to distort",
      "meaning_uk": "перекручувати",
      "meaning_es": "dar una interpretación falsa a algo",
      "example": "No permitas que intenten *** tus palabras en la entrevista."
    },
    {
      "term": "la pluralidad",
      "type": "Noun",
      "meaning_tr": "çoğulculuk",
      "meaning_en": "plurality",
      "meaning_uk": "плюралізм",
      "meaning_es": "existencia de diversas opiniones",
      "example": "Una democracia sana necesita *** de voces en los medios."
    },
    {
      "term": "riguroso",
      "type": "Adjective",
      "meaning_tr": "titiz",
      "meaning_en": "rigorous",
      "meaning_uk": "ретельний",
      "meaning_es": "que muestra gran exactitud",
      "example": "El periodista realizó un trabajo *** sobre el caso de corrupción."
    },
    {
      "term": "la audiencia",
      "type": "Noun",
      "meaning_tr": "izleyici kitlesi",
      "meaning_en": "audience",
      "meaning_uk": "аудиторія",
      "meaning_es": "público que recibe un mensaje",
      "example": "La *** exige contenidos de mayor calidad y profundidad."
    },
    {
      "term": "tergiversado",
      "type": "Adjective",
      "meaning_tr": "saptırılmış",
      "meaning_en": "distorted",
      "meaning_uk": "перекручений",
      "meaning_es": "que ha sido interpretado falsamente",
      "example": "El mensaje final quedó totalmente *** tras la edición."
    },
    {
      "term": "la veracidad",
      "type": "Noun",
      "meaning_tr": "doğruluk",
      "meaning_en": "truthfulness",
      "meaning_uk": "правдивість",
      "meaning_es": "cualidad de ser verdadero",
      "example": "Debemos cuestionar *** de los datos presentados."
    },
    {
      "term": "omitir",
      "type": "Verb",
      "meaning_tr": "atlamak",
      "meaning_en": "to omit",
      "meaning_uk": "опускати",
      "meaning_es": "dejar de decir o hacer algo",
      "example": "Decidieron *** los detalles más polémicos de la noticia."
    },
    {
      "term": "el trasfondo",
      "type": "Noun",
      "meaning_tr": "arka plan",
      "meaning_en": "background",
      "meaning_uk": "підґрунтя",
      "meaning_es": "lo que hay detrás de un hecho",
      "example": "Hay un *** político en esta decisión mediática."
    },
    {
      "term": "cuestionable",
      "type": "Adjective",
      "meaning_tr": "tartışmalı",
      "meaning_en": "questionable",
      "meaning_uk": "сумнівний",
      "meaning_es": "que puede ser objeto de duda",
      "example": "La ética de este presentador es bastante ***."
    },
    {
      "term": "la manipulación",
      "type": "Noun",
      "meaning_tr": "manipülasyon",
      "meaning_en": "manipulation",
      "meaning_uk": "маніпуляція",
      "meaning_es": "acción de manipular",
      "example": "La *** de las imágenes cambió el sentido de la historia."
    },
    {
      "term": "difamatorio",
      "type": "Adjective",
      "meaning_tr": "iftira niteliğinde",
      "meaning_en": "defamatory",
      "meaning_uk": "наклепницький",
      "meaning_es": "que desacredita a alguien",
      "example": "El artículo fue considerado *** por la persona afectada."
    },
    {
      "term": "la parcialidad",
      "type": "Noun",
      "meaning_tr": "taraflılık",
      "meaning_en": "partiality",
      "meaning_uk": "упередженість",
      "meaning_es": "falta de objetividad",
      "example": "Su *** quedó clara al omitir la opinión del oponente."
    },
    {
      "term": "sesgar",
      "type": "Verb",
      "meaning_tr": "yönlendirmek",
      "meaning_en": "to bias",
      "meaning_uk": "схиляти",
      "meaning_es": "dar un enfoque parcial",
      "example": "Es fácil *** la información si solo consultas una fuente."
    },
    {
      "term": "el enfoque",
      "type": "Noun",
      "meaning_tr": "yaklaşım",
      "meaning_en": "approach/focus",
      "meaning_uk": "підхід",
      "meaning_es": "manera de considerar un asunto",
      "example": "El *** de la noticia fue demasiado superficial."
    },
    {
      "term": "rigurosamente",
      "type": "Adverb",
      "meaning_tr": "titizlikle",
      "meaning_en": "rigorously",
      "meaning_uk": "ретельно",
      "meaning_es": "de manera rigurosa",
      "example": "Los datos fueron analizados *** antes de su publicación."
    },
    {
      "term": "la ética",
      "type": "Noun",
      "meaning_tr": "etik",
      "meaning_en": "ethics",
      "meaning_uk": "етика",
      "meaning_es": "conjunto de normas morales",
      "example": "La *** periodística prohíbe inventar fuentes."
    },
    {
      "term": "transparente",
      "type": "Adjective",
      "meaning_tr": "şeffaf",
      "meaning_en": "transparent",
      "meaning_uk": "прозорий",
      "meaning_es": "claro y sin ocultamientos",
      "example": "Los medios deben ser *** sobre quién financia su actividad."
    },
    {
      "term": "la primicia",
      "type": "Noun",
      "meaning_tr": "ilk haber",
      "meaning_en": "scoop",
      "meaning_uk": "сенсаційна новина",
      "meaning_es": "noticia que se publica por primera vez",
      "example": "El canal anunció *** antes que nadie."
    },
    {
      "term": "subjetivo",
      "type": "Adjective",
      "meaning_tr": "öznel",
      "meaning_en": "subjective",
      "meaning_uk": "суб'єктивний",
      "meaning_es": "que depende del modo de pensar de cada uno",
      "example": "El comentario del presentador fue muy ***."
    },
    {
      "term": "al menos",
      "type": "Adverb",
      "meaning_tr": "en azından",
      "meaning_en": "at least",
      "meaning_uk": "принаймні",
      "meaning_es": "por lo menos",
      "example": "Debes leer *** tres periódicos distintos para informarte bien."
    },
    {
      "term": "aunque",
      "type": "Conjunction",
      "meaning_tr": "rağmen",
      "meaning_en": "although",
      "meaning_uk": "хоча",
      "meaning_es": "a pesar de que",
      "example": "La noticia es importante, *** no fue confirmada aún."
    },
    {
      "term": "puesto que",
      "type": "Conjunction",
      "meaning_tr": "çünkü",
      "meaning_en": "since/because",
      "meaning_uk": "оскільки",
      "meaning_es": "ya que",
      "example": "Debemos ser críticos, *** los medios no siempre dicen la verdad."
    },
    {
      "term": "debido a",
      "type": "Preposition",
      "meaning_tr": "nedeniyle",
      "meaning_en": "due to",
      "meaning_uk": "через",
      "meaning_es": "a causa de",
      "example": "La noticia fue retirada *** errores en la fuente original."
    },
    {
      "term": "el titular",
      "type": "Noun",
      "meaning_tr": "başlık",
      "meaning_en": "headline",
      "meaning_uk": "заголовок",
      "meaning_es": "título de una noticia",
      "example": "A veces *** es más impactante que el contenido mismo."
    },
    {
      "term": "la credibilidad",
      "type": "Noun",
      "meaning_tr": "güvenilirlik",
      "meaning_en": "credibility",
      "meaning_uk": "довіра",
      "meaning_es": "cualidad de ser creíble",
      "example": "La *** de ese medio ha disminuido drásticamente."
    },
    {
      "term": "contrastable",
      "type": "Adjective",
      "meaning_tr": "doğrulanabilir",
      "meaning_en": "verifiable",
      "meaning_uk": "перевірюваний",
      "meaning_es": "que se puede comprobar",
      "example": "Toda información debe ser *** con datos oficiales."
    },
    {
      "term": "la fuente",
      "type": "Noun",
      "meaning_tr": "kaynak",
      "meaning_en": "source",
      "meaning_uk": "джерело",
      "meaning_es": "principio de donde proviene algo",
      "example": "El periodista decidió proteger a su *** confidencial."
    },
    {
      "term": "la veracidad",
      "type": "Noun",
      "meaning_tr": "doğruluk",
      "meaning_en": "truthfulness",
      "meaning_uk": "правдивість",
      "meaning_es": "exactitud de los hechos",
      "example": "Poner en duda *** de la información es un acto de responsabilidad."
    },
    {
      "term": "falsificar",
      "type": "Verb",
      "meaning_tr": "sahtesini yapmak",
      "meaning_en": "to falsify",
      "meaning_uk": "підробляти",
      "meaning_es": "hacer pasar por verdadero lo falso",
      "example": "Fue acusado de *** documentos para crear una noticia falsa."
    },
    {
      "term": "mediático",
      "type": "Adjective",
      "meaning_tr": "medya ile ilgili",
      "meaning_en": "media-related",
      "meaning_uk": "медійний",
      "meaning_es": "relativo a los medios de comunicación",
      "example": "El evento tuvo un gran impacto *** en toda la región."
    }
  ]
}